src/pe.v
`timescale 1ns/10ps

module processing_element 
    # (parameter PRECISION = 8,
       parameter OUTPUT_PRECISION = 32)
    (
        CLK,
        s_in,
        s_out,
        a_in,
        b_in,
        start_multiply,
        pe_ready,
        pe_ack
        );

	input CLK;
    output reg pe_ready = 0;
	input [PRECISION-1:0] a_in, b_in;
	input start_multiply;
    input [OUTPUT_PRECISION-1:0] s_in;
	output reg [OUTPUT_PRECISION-1:0] s_out;
    input pe_ack;

	always @(posedge CLK) begin
        if (pe_ack) begin 
            pe_ready <= 0;
        end
        else begin
            if (start_multiply) begin 
                s_out = s_in + a_in * b_in;
                pe_ready = 1;
            end
        end
	end
endmodule

src/pe_message_passer.v
`timescale 1ns/10ps
`include "pe.v"

module message_passer 
    # (parameter PRECISION = 8,
       parameter OUTPUT_PRECISION = 32)
    (
        CLK,
        ready,
        ack,
        A,
        B,
        s_out,
        isu,
        osu,
        isl,
        osl,
        isd,
        osd,
        isr,
        osr,
        image_to_shift,
        a_overwrite,
        b_overwrite,
        s_out_overwrite,
        shift_direction,
        command_to_execute);
    //CLK here is the CLK
    //reset is a chip wide reset. All registers should dump their data
    //s_out is the output product of the array
    //isu is input shift up. This input is where data that will be shifted from below comes from.
    //osu is output shift up. This is where data that we want to shift up goes. 
    //The ready signal is raised after either a multiply or a shift. It is set to zero when a new operation is raised (shift_left, shift_right, shift_up,shift_down, start_multiply rise)
    //shift_direction is a 2 bit signal with the directions being: 00-up, 01-down, 10-left, 11-right
    //command_to_execute determines what we are going to do on this clock cycle. Here are the commands:
    //000 - multiply
    //001 - shift_up
    //010 - shift_down
    //011 - shift_left
    //100 - shift_right
    //101 - Overwrite A and B values
    //110 - Overwrite S_out values
    //111 - reset

	input CLK;
    output reg ready = 0;
    input start;
    input ack;
    input [1:0] shift_direction;
    input [2:0] command_to_execute;

    output reg [PRECISION-1:0] A = 0;
    output reg [PRECISION-1:0] B = 0;
    output reg [OUTPUT_PRECISION-1:0] s_out = 0;

    input [PRECISION-1:0] isl;
    input [PRECISION-1:0] isu;
    input [PRECISION-1:0] isr;
    input [PRECISION-1:0] isd;
    
    output reg [PRECISION-1:0] osl = 0;
    output reg [PRECISION-1:0] osd = 0;
    output reg [PRECISION-1:0] osr = 0;
    output reg [PRECISION-1:0] osu = 0;

    input image_to_shift;

    input [PRECISION-1:0] a_overwrite;
    input [PRECISION-1:0] b_overwrite;
    input [OUTPUT_PRECISION-1:0] s_out_overwrite;

    reg start_multiply;
    wire [OUTPUT_PRECISION-1:0] returned_from_pe;
    wire pe_ready;
    reg pe_ack;
    //Here we instantiate an instance of a pe
    processing_element #(.PRECISION(PRECISION), .OUTPUT_PRECISION(OUTPUT_PRECISION)) pe_inst (.CLK(CLK),.s_in(s_out),.s_out(returned_from_pe),.a_in(A),.b_in(B),.start_multiply(start_multiply),.pe_ready(pe_ready),.pe_ack(pe_ack));

	always @(posedge CLK) begin
        if (ack) begin 
            ready <= 0;
        end
        else begin
            //On each clock cycle we check command_to_execute and use that in a case statement        
            if (command_to_execute == 3'b000) begin //000 - multiply
                pe_ack = 1;
                pe_ack <= 0;
                start_multiply <= 1'b1;
                wait (pe_ready == 1);
                s_out = returned_from_pe;
                start_multiply = 1'b0;
                ready = 1;
            end
            else if (command_to_execute == 3'b001) begin  //001 - shift_up
                if (image_to_shift == 0) begin
                    osu = A;
                    A = isu;
                    ready = 1;
                end
                else if (image_to_shift == 1) begin
                    osu = B;
                    B = isu;
                    ready = 1;
                end
            end
            else if (command_to_execute == 3'b010) begin //010 - shift_down
                if (image_to_shift == 0) begin
                    osd = A;
                    A = isd;
                    ready = 1;
                end
                else if (image_to_shift == 1) begin
                    osd = B;
                    B = isd;
                    ready = 1;
                end
            end
            else if (command_to_execute == 3'b011) begin //011 - shift_left
                if (image_to_shift == 0) begin
                    osl = A;
                    A = isl;
                    ready = 1;
                end
                else if (image_to_shift == 1) begin
                    osl = B;
                    B = isl;
                    ready = 1;
                end
            end
            else if (command_to_execute == 3'b100) begin //100 - shift_right
                if (image_to_shift == 0) begin
                    osr = A;
                    A = isr;
                    ready = 1;
                end
                else if (image_to_shift == 1) begin
                    osr = B;
                    B = isr;
                    ready = 1;
                end
            end
            else if (command_to_execute == 3'b101) begin //101 - Overwrite A and B values
                A = a_overwrite;
                B = b_overwrite;
                ready = 1;
            end
            else if (command_to_execute == 3'b110) begin //110 - Overwrite S_out values
                s_out = s_out_overwrite;
                ready = 1;
            end
            else if (command_to_execute == 3'b111) begin //111 - reset
                A = {PRECISION{1'b0}};
                B = {PRECISION{1'b0}};
                s_out = {OUTPUT_PRECISION{1'b0}};
                ready = 1'b1;
            end
        end 
    end 
endmodule

src/pe_message_passer_tb.v
// Multi-precision adder test-bench
module processing_element_tb ();

	parameter CLOCK_PERIOD = 100; // 10 MHz clock
	parameter NUM_TEST = 10; // Number of tests

	reg sys_clk;
	wire ready;
	reg start;
	reg [9:0] test_err;
	reg [9:0] test_count;

	reg [7:0] isu = 0;
	wire [7:0] osu;
	reg [7:0] isl = 0;
	wire [7:0] osl;
	reg [7:0] isd = 0;
	wire [7:0] osd;
	reg [7:0] isr = 0;
	wire [7:0] osr;
	wire [31:0] s_out;
	reg [7:0] a_overwrite = 0;
	reg [7:0] b_overwrite = 0;
	reg [31:0] s_out_overwrite = 0;
	reg [1:0] shift_direction = 0;
	reg [2:0] command_to_execute = 0;
	reg image_to_shift;
	wire [7:0] A;
	wire [7:0] B;
	reg ack;

	event terminate_sim;

	// Modify the module name for the design being tested

	message_passer #(.PRECISION(8),.OUTPUT_PRECISION(32)) u_DUT  (
        .CLK(sys_clk),
		.ready(ready),
		.ack(ack),
		.A(A),
		.B(B),
        .s_out(s_out),
        .isu(isu),
        .osu(osu),
        .isl(isl),
        .osl(osl),
        .isd(isd),
        .osd(osd),
        .isr(isr),
        .osr(osr),
        .a_overwrite(a_overwrite),
        .b_overwrite(b_overwrite),
        .s_out_overwrite(s_out_overwrite),
        .shift_direction(shift_direction),
		.image_to_shift(image_to_shift),
        .command_to_execute(command_to_execute)
		);

	always @(posedge sys_clk) begin
		if (test_count == NUM_TEST) begin
					-> terminate_sim;
		end
		else if (test_count == 0) begin
			//Test shift up
			ack = 1;
			$display("Performing Test (%d)", test_count);
			isu <= 8'b01101001;
			image_to_shift <= 1'b0;
			command_to_execute <= 3'b001;
			ack <= 0;
			wait (ready == 1)
			if (osu != 8'b0 || A != 8'b01101001) begin
				$display("Shift up of A meant to be 01101001 is A=(%d), osu=(%d)",A, osu);
				$display("ERROR (%d)", test_count);
				test_err <= test_err + 1;
			end
			test_count = test_count + 1;
		end
		else if (test_count == 1) begin
			//Test shift down
			ack = 1;
			wait (ready == 0)
			$display("Performing Test (%d)", test_count);
			isd <= 8'b00000111;
			image_to_shift <= 1'b0;
			command_to_execute <= 3'b010;
			ack <= 0;
			wait (ready == 1)
			if (osd != 8'b01101001 || A != 8'b00000111) begin
				$display("Shift up of A meant to be 00000111 is A=(%d), osd=(%d)",A, osd);
				$display("ERROR (%d)", test_count);
				test_err <= test_err + 1;
			end
			test_count = test_count + 1;
		end
		else if (test_count == 2) begin
			//Test shift left
			ack = 1;
			wait (ready == 0)
			$display("Performing Test (%d)", test_count);
			isl <= 8'b10000110;
			image_to_shift <= 1'b1;
			command_to_execute <= 3'b011;
			ack <= 0;
			wait (ready == 1)
			if (osl != 8'b0 || B != 8'b10000110) begin
				$display("Shift up of B meant to be 01101001 is B=(%d), osl=(%d)",B, osl);
				$display("ERROR (%d)", test_count);
				test_err <= test_err + 1;
			end
			test_count <= test_count + 1;
		end
		else if (test_count == 3) begin
			//Test shift right
			ack = 1;
			wait (ready == 0)
			$display("Performing Test (%d)", test_count);
			isr <= 8'b10100110;
			image_to_shift <= 1'b1;
			command_to_execute <= 3'b100;
			ack <= 0;
			wait (ready == 1)
			if (osr != 8'b10000110 || B != 8'b10100110) begin
				$display("Shift up of B meant to be 01101001 is B=(%d), osr=(%d)",B, osr);
				$display("ERROR (%d)", test_count);
				test_err <= test_err + 1;
			end
			test_count <= test_count + 1;
		end
		else if (test_count == 4) begin
			//Test multiplier. We already have preloaded in some values
			ack = 1;
			wait (ready == 0)
			$display("Performing Test (%d)", test_count);
			command_to_execute <= 3'b000;
			ack <= 0;
			wait (ready == 1)
			$display("Multiplier test result:(%d)",s_out);
			if (s_out != 32'b010010001010) begin
				$display("ERROR (%d)", test_count);
				$display("Multiplier test result:(%d)",s_out);
				test_err <= test_err + 1;
			end
			test_count <= test_count + 1;
		end
		else if (test_count == 5) begin
			//Test overwrite A and B
			ack = 1;
			wait (ready == 0)
			$display("Performing Test (%d)", test_count);
			a_overwrite <= 8'b00111101;
			b_overwrite <= 8'b01110001;
			command_to_execute <= 3'b101;
			ack <= 0;
			wait (ready == 1)
			if (A != 8'b00111101 || B!= 8'b01110001) begin
				$display("ERROR (%d)", test_count);
				test_err <= test_err + 1;
			end
			test_count <= test_count + 1;
		end
		else if (test_count == 6) begin
			//Test Overwrite S_out
			ack = 1;
			wait (ready == 0)
			$display("Performing Test (%d)", test_count);
			s_out_overwrite <= 32'b01011101111101100100100101000100;
			command_to_execute <= 3'b110;
			ack = 0;
			wait (ready == 1)
			if (s_out != 32'b01011101111101100100100101000100) begin
				$display("ERROR (%d)", test_count);
				test_err <= test_err + 1;
			end
			test_count <= test_count + 1;
		end
		else if (test_count == 7) begin
			//Test Reset
			ack = 1;
			wait (ready == 0)
			$display("Performing Test (%d)", test_count);
			command_to_execute <= 3'b111;
			ack = 0;
			wait (ready == 1)
			if (A != 8'b0 || B != 8'b0 || s_out != 8'b0) begin
				$display("ERROR (%d)", test_count);
				test_err <= test_err + 1;
			end
			test_count <= test_count + 1;
		end
		else begin
			test_count <= test_count + 1;
		end
    end

	// End of simulation
    	initial @(terminate_sim) begin
        	$display("END OF SIMULATION (Time: %g ns)", $time);
        	if(test_err == 0) begin
            		$display("TEST RESULT: PASS (%d / %d)", test_count, test_count);
        	end
        	else begin
            		$display("TEST RESULT: FAIL (%d / %d)", test_err, test_count);
        	end
        	$display("##################\n");
        	#1  $finish;
    	end

	// Initial conditions
	initial begin
	    sys_clk = 1'b0;
        test_err = 0; test_count = 0;
		#(CLOCK_PERIOD/2) $display("START OF SIMULATION (Time: %g ns)", $time);
    	end


	// VCD dump
	initial begin
		$dumpfile("mpadd.vcd");
		$dumpvars(0, u_DUT);
	end

	// System clock generator
	always begin
		#(CLOCK_PERIOD/2) sys_clk = ~sys_clk;
	end

endmodule

src/mpadd.vcd
$date
	Sat Nov 23 17:31:17 2019
$end
$version
	Icarus Verilog
$end
$timescale
	10ps
$end
$scope module processing_element_tb $end
$scope module u_DUT $end
$var wire 1 ! CLK $end
$var wire 8 " a_overwrite [7:0] $end
$var wire 1 # ack $end
$var wire 8 $ b_overwrite [7:0] $end
$var wire 3 % command_to_execute [2:0] $end
$var wire 1 & image_to_shift $end
$var wire 8 ' isd [7:0] $end
$var wire 8 ( isl [7:0] $end
$var wire 8 ) isr [7:0] $end
$var wire 8 * isu [7:0] $end
$var wire 32 + s_out_overwrite [31:0] $end
$var wire 2 , shift_direction [1:0] $end
$var wire 1 - start $end
$var wire 32 . returned_from_pe [31:0] $end
$var wire 1 / pe_ready $end
$var reg 8 0 A [7:0] $end
$var reg 8 1 B [7:0] $end
$var reg 8 2 osd [7:0] $end
$var reg 8 3 osl [7:0] $end
$var reg 8 4 osr [7:0] $end
$var reg 8 5 osu [7:0] $end
$var reg 1 6 pe_ack $end
$var reg 1 7 ready $end
$var reg 32 8 s_out [31:0] $end
$var reg 1 9 start_multiply $end
$scope module pe_inst $end
$var wire 1 ! CLK $end
$var wire 8 : a_in [7:0] $end
$var wire 8 ; b_in [7:0] $end
$var wire 1 6 pe_ack $end
$var wire 32 < s_in [31:0] $end
$var wire 1 9 start_multiply $end
$var reg 1 / pe_ready $end
$var reg 32 = s_out [31:0] $end
$upscope $end
$upscope $end
$upscope $end
$enddefinitions $end
#0
$dumpvars
bx =
b0 <
b0 ;
b0 :
x9
b0 8
07
x6
b0 5
b0 4
b0 3
b0 2
b0 1
b0 0
0/
bx .
z-
b0 ,
b0 +
b0 *
b0 )
b0 (
b0 '
x&
b0 %
b0 $
x#
b0 "
0!
$end
#5000000000000
b1 %
0&
b1101001 *
0#
1!
#10000000000000
0!
#15000000000000
17
b1101001 0
b1101001 :
1!
#20000000000000
0!
#25000000000000
b10 %
b111 '
07
0#
1!
#30000000000000
0!
#35000000000000
17
b111 0
b111 :
b1101001 2
1!
#40000000000000
0!
#45000000000000
b11 %
1&
b10000110 (
07
0#
1!
#50000000000000
0!
#55000000000000
17
b10000110 1
b10000110 ;
1!
#60000000000000
0!
#65000000000000
b100 %
b10100110 )
07
0#
1!
#70000000000000
0!
#75000000000000
17
b10100110 1
b10100110 ;
b10000110 4
1!
#80000000000000
0!
#85000000000000
b0 %
07
0#
1!
#90000000000000
0!
#95000000000000
19
06
1!
#100000000000000
0!
#105000000000000
17
09
b10010001010 8
b10010001010 <
1/
b10010001010 .
b10010001010 =
1!
#110000000000000
0!
#115000000000000
b101 %
b1110001 $
b111101 "
07
0#
1!
#120000000000000
0!
#125000000000000
17
b1110001 1
b1110001 ;
b111101 0
b111101 :
1!
#130000000000000
0!
#135000000000000
b110 %
b1011101111101100100100101000100 +
07
0#
1!
#140000000000000
0!
#145000000000000
17
b1011101111101100100100101000100 8
b1011101111101100100100101000100 <
1!
#150000000000000
0!
#155000000000000
b111 %
07
0#
1!
#160000000000000
0!
#165000000000000
17
b0 8
b0 <
b0 1
b0 ;
b0 0
b0 :
1!
